churros/client/__init__.py
churros-0.6.0.dist-info/METADATA
churros-0.6.0.dist-info/WHEEL
churros-0.6.0.dist-info/RECORD
