Metadata-Version: 2.1
Name: churros
Version: 0.6.0
Summary: Official Churros OAuth2 client
License: MIT
Author: Churros developers
Author-email: contact@net7.dev
Requires-Python: >=3.11,<4.0
Classifier: License :: OSI Approved :: MIT License
Classifier: Programming Language :: Python :: 3
Classifier: Programming Language :: Python :: 3.11
Classifier: Programming Language :: Python :: 3.12
Requires-Dist: requests (>=2.31.0,<3.0.0)
